{"players": {"1": {"id": 1, "firstname": "azerty", "lastname": "", "date_of_birth": "", "sexe": "", "rank": "1"}, "2": {"id": 2, "firstname": "njn", "lastname": "", "date_of_birth": "", "sexe": "", "rank": "2"}, "3": {"id": 3, "firstname": "bhuiujhnb", "lastname": "", "date_of_birth": "", "sexe": "", "rank": "3"}, "4": {"id": 4, "firstname": "qsdfg", "lastname": "", "date_of_birth": "", "sexe": "", "rank": "4"}, "5": {"id": 5, "firstname": "njiop", "lastname": "", "date_of_birth": "", "sexe": "", "rank": "5"}, "6": {"id": 6, "firstname": "ujnhgtrf", "lastname": "", "date_of_birth": "", "sexe": "", "rank": "6"}, "7": {"id": 7, "firstname": "frea", "lastname": "", "date_of_birth": "", "sexe": "", "rank": "7"}, "8": {"id": 8, "firstname": "ryuiop", "lastname": "", "date_of_birth": "", "sexe": "", "rank": "8"}}, "playerbytournement": {"1": {"idtournament": 1, "idplayer": "1"}, "2": {"idtournament": 1, "idplayer": "2"}, "3": {"idtournament": 1, "idplayer": "3"}, "4": {"idtournament": 1, "idplayer": "4"}, "5": {"idtournament": 1, "idplayer": "5"}, "6": {"idtournament": 1, "idplayer": "6"}, "7": {"idtournament": 1, "idplayer": "7"}, "8": {"idtournament": 1, "idplayer": "8"}, "9": {"idtournament": 9, "idplayer": "1"}, "10": {"idtournament": 9, "idplayer": "2"}, "11": {"idtournament": 9, "idplayer": "3"}, "12": {"idtournament": 9, "idplayer": "4"}, "13": {"idtournament": 9, "idplayer": "5"}, "14": {"idtournament": 9, "idplayer": "6"}, "15": {"idtournament": 9, "idplayer": "7"}, "16": {"idtournament": 9, "idplayer": "8"}, "17": {"idtournament": 17, "idplayer": "1"}, "18": {"idtournament": 18, "idplayer": "1"}, "19": {"idtournament": 18, "idplayer": "2"}, "20": {"idtournament": 18, "idplayer": "3"}, "21": {"idtournament": 18, "idplayer": "4"}, "22": {"idtournament": 18, "idplayer": "5"}, "23": {"idtournament": 18, "idplayer": "6"}, "24": {"idtournament": 18, "idplayer": "7"}, "25": {"idtournament": 18, "idplayer": "8"}, "26": {"idtournament": 26, "idplayer": "1"}, "27": {"idtournament": 26, "idplayer": "2"}, "28": {"idtournament": 26, "idplayer": "3"}, "29": {"idtournament": 26, "idplayer": "4"}, "30": {"idtournament": 26, "idplayer": "5"}, "31": {"idtournament": 26, "idplayer": "6"}, "32": {"idtournament": 26, "idplayer": "7"}, "33": {"idtournament": 26, "idplayer": "8"}, "34": {"idtournament": 34, "idplayer": "1"}, "35": {"idtournament": 34, "idplayer": "2"}, "36": {"idtournament": 34, "idplayer": "3"}, "37": {"idtournament": 34, "idplayer": "4"}, "38": {"idtournament": 34, "idplayer": "5"}, "39": {"idtournament": 34, "idplayer": "6"}, "40": {"idtournament": 34, "idplayer": "7"}, "41": {"idtournament": 34, "idplayer": "8"}, "42": {"idtournament": 42, "idplayer": "1"}, "43": {"idtournament": 42, "idplayer": "2"}, "44": {"idtournament": 42, "idplayer": "3"}, "45": {"idtournament": 42, "idplayer": "4"}, "46": {"idtournament": 42, "idplayer": "5"}, "47": {"idtournament": 42, "idplayer": "6"}, "48": {"idtournament": 42, "idplayer": "7"}, "49": {"idtournament": 42, "idplayer": "8"}, "50": {"idtournament": 50, "idplayer": "1"}, "51": {"idtournament": 50, "idplayer": "2"}, "52": {"idtournament": 50, "idplayer": "3"}, "53": {"idtournament": 50, "idplayer": "4"}, "54": {"idtournament": 50, "idplayer": "5"}, "55": {"idtournament": 50, "idplayer": "6"}, "56": {"idtournament": 50, "idplayer": "7"}, "57": {"idtournament": 50, "idplayer": "8"}, "58": {"idtournament": 58, "idplayer": "1"}, "59": {"idtournament": 58, "idplayer": "2"}, "60": {"idtournament": 58, "idplayer": "3"}, "61": {"idtournament": 58, "idplayer": "4"}, "62": {"idtournament": 58, "idplayer": "5"}, "63": {"idtournament": 58, "idplayer": "6"}, "64": {"idtournament": 58, "idplayer": "7"}, "65": {"idtournament": 58, "idplayer": "8"}, "66": {"idtournament": 66, "idplayer": "1"}, "67": {"idtournament": 66, "idplayer": "2"}, "68": {"idtournament": 66, "idplayer": "3"}, "69": {"idtournament": 66, "idplayer": "4"}, "70": {"idtournament": 66, "idplayer": "5"}, "71": {"idtournament": 66, "idplayer": "6"}, "72": {"idtournament": 66, "idplayer": "7"}, "73": {"idtournament": 66, "idplayer": "8"}, "74": {"idtournament": 74, "idplayer": "1"}, "75": {"idtournament": 74, "idplayer": "2"}, "76": {"idtournament": 74, "idplayer": "3"}, "77": {"idtournament": 74, "idplayer": "4"}, "78": {"idtournament": 74, "idplayer": "5"}, "79": {"idtournament": 74, "idplayer": "6"}, "80": {"idtournament": 74, "idplayer": "7"}, "81": {"idtournament": 74, "idplayer": "8"}, "82": {"idtournament": 82, "idplayer": "1"}, "83": {"idtournament": 82, "idplayer": "2"}, "84": {"idtournament": 82, "idplayer": "3"}, "85": {"idtournament": 82, "idplayer": "4"}, "86": {"idtournament": 82, "idplayer": "5"}, "87": {"idtournament": 82, "idplayer": "6"}, "88": {"idtournament": 82, "idplayer": "7"}, "89": {"idtournament": 82, "idplayer": "8"}, "90": {"idtournament": 90, "idplayer": "1"}, "91": {"idtournament": 90, "idplayer": "2"}, "92": {"idtournament": 90, "idplayer": "3"}, "93": {"idtournament": 90, "idplayer": "4"}, "94": {"idtournament": 90, "idplayer": "5"}, "95": {"idtournament": 90, "idplayer": "6"}, "96": {"idtournament": 90, "idplayer": "7"}, "97": {"idtournament": 90, "idplayer": "8"}}}